adventofcode/utils/Point2D.py
adventofcode/utils/Point3D.py
adventofcode/utils/Stack.py
adventofcode/utils/__init__.py
adventofcode.utils-2.0.0.dist-info/METADATA
adventofcode.utils-2.0.0.dist-info/WHEEL
adventofcode.utils-2.0.0.dist-info/top_level.txt
adventofcode.utils-2.0.0.dist-info/RECORD
