Metadata-Version: 2.1
Name: adventofcode.utils
Version: 2.0.0
Summary: Advent of Code utility classes
Home-page: https://github.com/dh256/adventofcode/tree/master/utils
Author: David Hanley
Author-email: hanley_d@hotmail.com
License: UNKNOWN
Platform: UNKNOWN
Classifier: Programming Language :: Python :: 3
Classifier: License :: OSI Approved :: MIT License
Classifier: Operating System :: OS Independent
Requires-Python: >=3.6
